examples/two_complete_meshes.mtl
examples/two_complete_meshes.obj
examples/untitled.mtl
examples/untitled.obj
examples/untitled_with_normals.mtl
examples/untitled_with_normals.obj
examples/untitled_with_normals_and_texcoords.mtl
examples/untitled_with_normals_and_texcoords.obj
wavefront_reader/__init__.py
wavefront_reader/wavefront_reader.py
wavefront_reader-0.1.0.dist-info/DESCRIPTION.rst
wavefront_reader-0.1.0.dist-info/METADATA
wavefront_reader-0.1.0.dist-info/RECORD
wavefront_reader-0.1.0.dist-info/WHEEL
wavefront_reader-0.1.0.dist-info/metadata.json
wavefront_reader-0.1.0.dist-info/top_level.txt
