Metadata-Version: 2.0
Name: wavefront-reader
Version: 0.1.0
Summary: A parser for wavefront .obj and .mtl files
Home-page: https://github.com/neuroneuro15/wavefront_reader
Author: Nicholas A. Del Grosso
Author-email: delgrosso@bio.lmu.de
License: MIT license
Keywords: wavefront_reader
Platform: UNKNOWN
Classifier: Development Status :: 2 - Pre-Alpha
Classifier: Intended Audience :: Developers
Classifier: License :: OSI Approved :: MIT License
Classifier: Natural Language :: English
Classifier: Programming Language :: Python :: 2
Classifier: Programming Language :: Python :: 2.7
Classifier: Programming Language :: Python :: 3
Classifier: Programming Language :: Python :: 3.5
Requires-Dist: numpy
